jsonplus/__init__.py
jsonplus-0.8.0.dist-info/DESCRIPTION.rst
jsonplus-0.8.0.dist-info/METADATA
jsonplus-0.8.0.dist-info/RECORD
jsonplus-0.8.0.dist-info/WHEEL
jsonplus-0.8.0.dist-info/metadata.json
jsonplus-0.8.0.dist-info/top_level.txt
