Metadata-Version: 1.1
Name: jsonplus
Version: 0.8.0
Summary: Custom datatypes (like datetime) serialization to/from JSON.
Home-page: https://github.com/randomir/jsonplus
Author: Radomir Stevanovic
Author-email: radomir.stevanovic@gmail.com
License: MIT
Keywords: json custom python type serialization deserialization datetime set
Platform: UNKNOWN
Classifier: Development Status :: 5 - Production/Stable
Classifier: Intended Audience :: Developers
Classifier: Programming Language :: Python
Classifier: Programming Language :: Python :: 2
Classifier: Programming Language :: Python :: 2.6
Classifier: Programming Language :: Python :: 2.7
Classifier: Programming Language :: Python :: 3
Classifier: Programming Language :: Python :: 3.3
Classifier: Programming Language :: Python :: 3.4
Classifier: Programming Language :: Python :: 3.5
Classifier: Programming Language :: Python :: 3.6
Classifier: License :: OSI Approved :: MIT License
Classifier: Operating System :: OS Independent
Classifier: Topic :: Software Development :: Libraries :: Python Modules
